ginput/__init__.py
ginput/command_line.py
ginput/ginput.py
ginput/keycodes.py
ginput_glisignoli-1.0.1.dist-info/LICENSE
ginput_glisignoli-1.0.1.dist-info/METADATA
ginput_glisignoli-1.0.1.dist-info/WHEEL
ginput_glisignoli-1.0.1.dist-info/entry_points.txt
ginput_glisignoli-1.0.1.dist-info/top_level.txt
ginput_glisignoli-1.0.1.dist-info/RECORD
