Metadata-Version: 2.1
Name: ginput-glisignoli
Version: 1.0.1
Summary: Send keystrokes to a virtual keyboard
Home-page: https://github.com/glisignoli/python-ginput
Author: Gino Lisignoli
Author-email: glisignoli@gmail.com
License: UNKNOWN
Project-URL: Bug Tracker, https://github.com/glisignoli/python-ginput/issues
Platform: any
Classifier: Development Status :: 4 - Beta
Classifier: Intended Audience :: Developers
Classifier: License :: OSI Approved :: GNU General Public License (GPL)
Classifier: Operating System :: POSIX
Classifier: Programming Language :: Python :: 3
Classifier: Topic :: Software Development :: Libraries
Requires-Python: >=3.10
License-File: LICENSE
Requires-Dist: libevdev (==0.10)
Requires-Dist: pyperclip (==1.8.2)
Provides-Extra: dev
Requires-Dist: autopep8 ; extra == 'dev'
